python/codepythoneasy.py
python/easyPy.py
python/easyPython.py
python/pyeasy.py
codepythoneasy-1.0.0.dist-info/METADATA
codepythoneasy-1.0.0.dist-info/WHEEL
codepythoneasy-1.0.0.dist-info/top_level.txt
codepythoneasy-1.0.0.dist-info/RECORD
