Metadata-Version: 2.1
Name: codepythoneasy
Version: 1.0.0
Summary: A simple Template for create python project
Author: ks lim
Author-email: kianseng.lim@sony.com
